ruly_dmn/__init__.py
ruly_dmn/common.py
ruly_dmn/dmn.py
ruly_dmn/main.py
ruly_dmn/handlers/__init__.py
ruly_dmn/handlers/camunda_modeler.py
ruly_dmn-0.0.6.dist-info/LICENSE
ruly_dmn-0.0.6.dist-info/METADATA
ruly_dmn-0.0.6.dist-info/WHEEL
ruly_dmn-0.0.6.dist-info/entry_points.txt
ruly_dmn-0.0.6.dist-info/top_level.txt
ruly_dmn-0.0.6.dist-info/RECORD
