Metadata-Version: 2.1
Name: ruly-dmn
Version: 0.0.6
Summary: DMN implementation with ruly rule engine
Home-page: https://github.com/ZlatSic/ruly-dmn
Author: Zlatan Sičanica
Author-email: zlatan.sicanica@gmail.com
License: UNKNOWN
Platform: UNKNOWN
Classifier: Development Status :: 1 - Planning
Classifier: Intended Audience :: Developers
Classifier: Intended Audience :: End Users/Desktop
Classifier: License :: OSI Approved :: MIT License
Classifier: Natural Language :: English
Classifier: Operating System :: OS Independent
Classifier: Programming Language :: Python :: 3 :: Only
Classifier: Topic :: Software Development :: Libraries
Classifier: Topic :: Utilities
Requires-Dist: ruly
